self_improving_agents/__init__.py
self_improving_agents/environment/__init__.py
self_improving_agents/environment/llm_environment.py
self_improving_agents/environment/snapshot.py
self_improving_agents/evaluator_handler/__init__.py
self_improving_agents/evaluator_handler/base.py
self_improving_agents/evaluator_handler/eval_pipeline.py
self_improving_agents/evaluator_handler/evaluator_saver.py
self_improving_agents/evaluator_handler/models.py
self_improving_agents/instrumentation/__init__.py
self_improving_agents/instrumentation/tracker.py
self_improving_agents/models/__init__.py
self_improving_agents/models/policy_update.py
self_improving_agents/models/snapshot.py
self_improving_agents/models/state_action.py
self_improving_agents/policy/__init__.py
self_improving_agents/policy/base.py
self_improving_agents/policy/llm_policy_updater.py
self_improving_agents/runners/README.md
self_improving_agents/runners/__init__.py
self_improving_agents/runners/arize_connector.py
self_improving_agents/runners/base.py
self_improving_agents/runners/data_collection_runner.py
self_improving_agents/runners/orchestrator.py
self_improving_agents/utils/__init__.py
self_improving_agents/utils/io.py
self_improving_agents-0.1.0.dist-info/METADATA
self_improving_agents-0.1.0.dist-info/WHEEL
self_improving_agents-0.1.0.dist-info/licenses/LICENSE
self_improving_agents-0.1.0.dist-info/RECORD
