Metadata-Version: 2.4
Name: self_improving_agents
Version: 0.1.0
Summary: A system for self improving agents.
Project-URL: Homepage, https://github.com/CakeCrusher/self_improving_agents
Project-URL: Bug Tracker, https://github.com/CakeCrusher/self_improving_agents/issues
Author-email: Your Name <your.email@example.com>
License: MIT
License-File: LICENSE
Classifier: License :: OSI Approved :: MIT License
Classifier: Operating System :: OS Independent
Classifier: Programming Language :: Python :: 3
Requires-Python: >=3.10
Requires-Dist: arize-otel>=0.8.0
Requires-Dist: arize-phoenix-evals>=0.20.4
Requires-Dist: arize>=7.36.1
Requires-Dist: pydantic>=2.11.2
Provides-Extra: dev
Requires-Dist: black>=23.0.0; extra == 'dev'
Requires-Dist: mypy>=1.0.0; extra == 'dev'
Requires-Dist: openai>=1.70.0; extra == 'dev'
Requires-Dist: openinference-instrumentation-openai>=0.1.23; extra == 'dev'
Requires-Dist: pre-commit>=3.0.0; extra == 'dev'
Requires-Dist: pytest>=7.0.0; extra == 'dev'
Requires-Dist: python-dotenv>=1.1.0; extra == 'dev'
Requires-Dist: ruff>=0.1.0; extra == 'dev'
